{
  "https://www.sinarharian.com.my/article/748948/berita/nasional/rm415-juta-wpp-disalur-kepada-27674-pelajar-ua-politeknik": [
    {
      "start": 0,
      "end": 12,
      "text": "KUALA LUMPUR",
      "label": "LOC",
      "score": 0.8337974548339844
    },
    {
      "start": 45,
      "end": 64,
      "text": "Ijazah Sarjana Muda",
      "label": "PRODUCT",
      "score": 0.5145151019096375
    },
    {
      "start": 100,
      "end": 115,
      "text": "Universiti Awam",
      "label": "ORG",
      "score": 0.7924670577049255
    },
    {
      "start": 125,
      "end": 135,
      "text": "Politeknik",
      "label": "ORG",
      "score": 0.815848171710968
    },
    {
      "start": 211,
      "end": 222,
      "text": "RM41.5 juta",
      "label": "MONEY",
      "score": 0.9406177997589111
    },
    {
      "start": 228,
      "end": 272,
      "text": "Perbadanan Tabung Pendidikan Tinggi Nasional",
      "label": "ORG",
      "score": 0.8167942762374878
    },
    {
      "start": 274,
      "end": 279,
      "text": "PTPTN",
      "label": "ORG",
      "score": 0.5867787599563599
    },
    {
      "start": 283,
      "end": 288,
      "text": "PTPTN",
      "label": "ORG",
      "score": 0.7117967009544373
    },
    {
      "start": 534,
      "end": 541,
      "text": "RM1,500",
      "label": "MONEY",
      "score": 0.9356881380081177
    },
    {
      "start": 962,
      "end": 967,
      "text": "PTPTN",
      "label": "ORG",
      "score": 0.7142711281776428
    },
    {
      "start": 1122,
      "end": 1135,
      "text": "RM1.46 bilion",
      "label": "MONEY",
      "score": 0.9688414335250854
    },
    {
      "start": 1156,
      "end": 1168,
      "text": "Kuala Lumpur",
      "label": "LOC",
      "score": 0.589023768901825
    },
    {
      "start": 1246,
      "end": 1261,
      "text": "universiti awam",
      "label": "ORG",
      "score": 0.5381950736045837
    },
    {
      "start": 1322,
      "end": 1327,
      "text": "PTPTN",
      "label": "ORG",
      "score": 0.5748092532157898
    },
    {
      "start": 1452,
      "end": 1478,
      "text": "Bank Islam Malaysia Berhad",
      "label": "ORG",
      "score": 0.7247711420059204
    },
    {
      "start": 1790,
      "end": 1795,
      "text": "PTPTN",
      "label": "ORG",
      "score": 0.6997037529945374
    },
    {
      "start": 1814,
      "end": 1819,
      "text": "PTPTN",
      "label": "ORG",
      "score": 0.6879029870033264
    },
    {
      "start": 1867,
      "end": 1880,
      "text": "Bukit Gelugor",
      "label": "LOC",
      "score": 0.7266284823417664
    },
    {
      "start": 1882,
      "end": 1894,
      "text": "Pulau Pinang",
      "label": "LOC",
      "score": 0.6879532933235168
    },
    {
      "start": 2022,
      "end": 2027,
      "text": "PTPTN",
      "label": "ORG",
      "score": 0.6877267956733704
    },
    {
      "start": 2029,
      "end": 2059,
      "text": "Datuk Seri Norliza Abdul Rahim",
      "label": "PERSON",
      "score": 0.6515280604362488
    },
    {
      "start": 2090,
      "end": 2102,
      "text": "Pulau Pinang",
      "label": "LOC",
      "score": 0.8294662833213806
    },
    {
      "start": 2104,
      "end": 2132,
      "text": "Muhammad Muhsin Abdul Rahman",
      "label": "PERSON",
      "score": 0.7341068983078003
    },
    {
      "start": 2152,
      "end": 2157,
      "text": "PTPTN",
      "label": "ORG",
      "score": 0.6276958584785461
    }
  ],
  "https://www.sinarharian.com.my/article/709458/berita/cetusan/usaha-hapuskan-riba-dalam-sistem-kewangan": [
    {
      "start": 20,
      "end": 32,
      "text": "Sinar Harian",
      "label": "PRODUCT",
      "score": 0.9057214260101318
    }
  ],
  "https://www.sinarharian.com.my/article/709376/bisnes/hapuskan-riba-dalam-sistem-kewangan": [
    {
      "start": 0,
      "end": 49,
      "text": "PERSIDANGAN Ekonomi dan Kewangan Islam Dunia ke-8",
      "label": "EVENT",
      "score": 0.5871236324310303
    },
    {
      "start": 51,
      "end": 56,
      "text": "WIEFC",
      "label": "EVENT",
      "score": 0.5861533880233765
    },
    {
      "start": 76,
      "end": 100,
      "text": "Universiti Minhaj Lahore",
      "label": "ORG",
      "score": 0.8397429585456848
    },
    {
      "start": 243,
      "end": 248,
      "text": "2,000",
      "label": "QUANTITY",
      "score": 0.6069162487983704
    },
    {
      "start": 385,
      "end": 394,
      "text": "Australia",
      "label": "GPE",
      "score": 0.7599471211433411
    },
    {
      "start": 396,
      "end": 403,
      "text": "Bahrain",
      "label": "GPE",
      "score": 0.728945791721344
    },
    {
      "start": 405,
      "end": 411,
      "text": "Brunei",
      "label": "GPE",
      "score": 0.7132523059844971
    },
    {
      "start": 413,
      "end": 418,
      "text": "Mesir",
      "label": "GPE",
      "score": 0.6537386775016785
    },
    {
      "start": 420,
      "end": 428,
      "text": "Perancis",
      "label": "GPE",
      "score": 0.6720287203788757
    },
    {
      "start": 430,
      "end": 434,
      "text": "Iran",
      "label": "GPE",
      "score": 0.6391798257827759
    },
    {
      "start": 436,
      "end": 441,
      "text": "Libya",
      "label": "GPE",
      "score": 0.6235941052436829
    },
    {
      "start": 443,
      "end": 451,
      "text": "Malaysia",
      "label": "GPE",
      "score": 0.7063047289848328
    },
    {
      "start": 453,
      "end": 464,
      "text": "New Zealand",
      "label": "GPE",
      "score": 0.6716428399085999
    },
    {
      "start": 466,
      "end": 473,
      "text": "Nigeria",
      "label": "GPE",
      "score": 0.6126108169555664
    },
    {
      "start": 485,
      "end": 490,
      "text": "Qatar",
      "label": "GPE",
      "score": 0.5556880831718445
    },
    {
      "start": 492,
      "end": 502,
      "text": "Arab Saudi",
      "label": "GPE",
      "score": 0.601667582988739
    },
    {
      "start": 504,
      "end": 518,
      "text": "United Kingdom",
      "label": "GPE",
      "score": 0.689703643321991
    },
    {
      "start": 523,
      "end": 539,
      "text": "Amerika Syarikat",
      "label": "GPE",
      "score": 0.6772539615631104
    },
    {
      "start": 624,
      "end": 659,
      "text": "Prof. Dr. Hussain Mohi-ud-Din Qadri",
      "label": "PERSON",
      "score": 0.8716380596160889
    },
    {
      "start": 719,
      "end": 743,
      "text": "Universiti Minhaj Lahore",
      "label": "ORG",
      "score": 0.6389455199241638
    },
    {
      "start": 887,
      "end": 895,
      "text": "Pakistan",
      "label": "LOC",
      "score": 0.6592687368392944
    },
    {
      "start": 1159,
      "end": 1167,
      "text": "Pakistan",
      "label": "LOC",
      "score": 0.5901371836662292
    },
    {
      "start": 1328,
      "end": 1336,
      "text": "Pakistan",
      "label": "LOC",
      "score": 0.52644944190979
    },
    {
      "start": 1401,
      "end": 1429,
      "text": "Mahkamah Syariah Persekutuan",
      "label": "ORG",
      "score": 0.730398416519165
    },
    {
      "start": 1456,
      "end": 1482,
      "text": "Pindaan Perlembagaan ke-26",
      "label": "EVENT",
      "score": 0.6521215438842773
    },
    {
      "start": 1607,
      "end": 1615,
      "text": "Pakistan",
      "label": "LOC",
      "score": 0.6197585463523865
    },
    {
      "start": 1830,
      "end": 1839,
      "text": "Nusantara",
      "label": "LOC",
      "score": 0.5433475375175476
    },
    {
      "start": 2334,
      "end": 2362,
      "text": "Mahkamah Syariah Persekutuan",
      "label": "ORG",
      "score": 0.6012541055679321
    },
    {
      "start": 2388,
      "end": 2417,
      "text": "Hakim Dr. Syed Muhammad Anwer",
      "label": "PERSON",
      "score": 0.5629239678382874
    },
    {
      "start": 2520,
      "end": 2528,
      "text": "Pakistan",
      "label": "LOC",
      "score": 0.5290672183036804
    }
  ],
  "https://www.sinarharian.com.my/article/709044/berita/nasional/malaysia-terus-kekal-teraju-kewangan-islam-dunia": [
    {
      "start": 0,
      "end": 12,
      "text": "KUALA LUMPUR",
      "label": "GPE",
      "score": 0.6902133822441101
    },
    {
      "start": 15,
      "end": 23,
      "text": "Malaysia",
      "label": "GPE",
      "score": 0.7814018130302429
    },
    {
      "start": 229,
      "end": 246,
      "text": "Dr Zulkifli Hasan",
      "label": "PERSON",
      "score": 0.8465719819068909
    },
    {
      "start": 256,
      "end": 264,
      "text": "Malaysia",
      "label": "GPE",
      "score": 0.7196853756904602
    },
    {
      "start": 364,
      "end": 374,
      "text": "Arab Saudi",
      "label": "GPE",
      "score": 0.7452486157417297
    },
    {
      "start": 382,
      "end": 402,
      "text": "Emiriah Arab Bersatu",
      "label": "GPE",
      "score": 0.5135024785995483
    },
    {
      "start": 415,
      "end": 424,
      "text": "Indonesia",
      "label": "GPE",
      "score": 0.6868460774421692
    },
    {
      "start": 434,
      "end": 442,
      "text": "Pakistan",
      "label": "GPE",
      "score": 0.6644119024276733
    },
    {
      "start": 466,
      "end": 474,
      "text": "Malaysia",
      "label": "GPE",
      "score": 0.5564808249473572
    },
    {
      "start": 553,
      "end": 563,
      "text": "Bank Islam",
      "label": "ORG",
      "score": 0.7675098180770874
    },
    {
      "start": 565,
      "end": 603,
      "text": "Universiti Islam Antarabangsa Malaysia",
      "label": "ORG",
      "score": 0.7915805578231812
    },
    {
      "start": 612,
      "end": 635,
      "text": "Amanah Ikhtiar Malaysia",
      "label": "ORG",
      "score": 0.8468050956726074
    },
    {
      "start": 721,
      "end": 750,
      "text": "Angkatan Belia Islam Malaysia",
      "label": "ORG",
      "score": 0.7161034941673279
    },
    {
      "start": 752,
      "end": 756,
      "text": "ABIM",
      "label": "ORG",
      "score": 0.5159964561462402
    },
    {
      "start": 759,
      "end": 802,
      "text": "Persatuan Kebangsaan Pelajar Islam Malaysia",
      "label": "ORG",
      "score": 0.8181341886520386
    },
    {
      "start": 815,
      "end": 836,
      "text": "Majlis Belia Malaysia",
      "label": "ORG",
      "score": 0.8075811862945557
    },
    {
      "start": 948,
      "end": 956,
      "text": "Malaysia",
      "label": "GPE",
      "score": 0.6785185933113098
    },
    {
      "start": 1120,
      "end": 1160,
      "text": "Perdana Menteri Datuk Seri Anwar Ibrahim",
      "label": "PERSON",
      "score": 0.7307668328285217
    },
    {
      "start": 1400,
      "end": 1408,
      "text": "Facebook",
      "label": "ORG",
      "score": 0.5281535387039185
    },
    {
      "start": 1523,
      "end": 1531,
      "text": "Malaysia",
      "label": "GPE",
      "score": 0.775943398475647
    },
    {
      "start": 1538,
      "end": 1558,
      "text": "Koperasi Belia Islam",
      "label": "ORG",
      "score": 0.8165034055709839
    },
    {
      "start": 1643,
      "end": 1646,
      "text": "KBI",
      "label": "ORG",
      "score": 0.5233187675476074
    },
    {
      "start": 1668,
      "end": 1672,
      "text": "ABIM",
      "label": "ORG",
      "score": 0.6234906315803528
    },
    {
      "start": 1702,
      "end": 1710,
      "text": "Malaysia",
      "label": "GPE",
      "score": 0.6638230085372925
    },
    {
      "start": 1793,
      "end": 1803,
      "text": "Bank Islam",
      "label": "ORG",
      "score": 0.720611572265625
    },
    {
      "start": 1826,
      "end": 1834,
      "text": "Malaysia",
      "label": "GPE",
      "score": 0.6893970966339111
    },
    {
      "start": 1836,
      "end": 1839,
      "text": "KBI",
      "label": "ORG",
      "score": 0.5168350338935852
    },
    {
      "start": 2007,
      "end": 2013,
      "text": "Nidzam",
      "label": "PERSON",
      "score": 0.7039727568626404
    },
    {
      "start": 2201,
      "end": 2214,
      "text": "Sultan Nazrin",
      "label": "PERSON",
      "score": 0.8210658431053162
    },
    {
      "start": 2288,
      "end": 2292,
      "text": "ABIM",
      "label": "ORG",
      "score": 0.7418850660324097
    }
  ],
  "https://www.sinarharian.com.my/article/708435/edisi/kelantan/bina-masjid-ibnu-batutah-hentian-musafir": [
    {
      "start": 0,
      "end": 10,
      "text": "KUALA KRAI",
      "label": "LOC",
      "score": 0.9078128337860107
    },
    {
      "start": 57,
      "end": 67,
      "text": "Kuala Krai",
      "label": "LOC",
      "score": 0.8299526572227478
    },
    {
      "start": 80,
      "end": 92,
      "text": "Ibnu Batutah",
      "label": "ORG",
      "score": 0.534863293170929
    },
    {
      "start": 108,
      "end": 142,
      "text": "Mukim Kecil Bandar Baru Kuala Krai",
      "label": "LOC",
      "score": 0.9108465313911438
    },
    {
      "start": 176,
      "end": 181,
      "text": "1,100",
      "label": "QUANTITY",
      "score": 0.6239067316055298
    },
    {
      "start": 246,
      "end": 256,
      "text": "Kuala Krai",
      "label": "LOC",
      "score": 0.7116044163703918
    },
    {
      "start": 259,
      "end": 269,
      "text": "Gua Musang",
      "label": "LOC",
      "score": 0.6650714874267578
    },
    {
      "start": 289,
      "end": 301,
      "text": "Ibnu Batutah",
      "label": "ORG",
      "score": 0.5624270439147949
    },
    {
      "start": 303,
      "end": 322,
      "text": "Dr Mohd Azmi Yaacob",
      "label": "PERSON",
      "score": 0.9248456358909607
    },
    {
      "start": 477,
      "end": 488,
      "text": "RM11.7 juta",
      "label": "MONEY",
      "score": 0.97514408826828
    },
    {
      "start": 582,
      "end": 592,
      "text": "Kuala Krai",
      "label": "LOC",
      "score": 0.6919053792953491
    },
    {
      "start": 595,
      "end": 605,
      "text": "Gua Musang",
      "label": "LOC",
      "score": 0.6233143210411072
    },
    {
      "start": 663,
      "end": 675,
      "text": "Kuala Lumpur",
      "label": "LOC",
      "score": 0.7416085600852966
    },
    {
      "start": 829,
      "end": 839,
      "text": "Kuala Krai",
      "label": "LOC",
      "score": 0.8355047702789307
    },
    {
      "start": 1511,
      "end": 1521,
      "text": "15 peratus",
      "label": "PERCENT",
      "score": 0.9094223380088806
    },
    {
      "start": 1606,
      "end": 1616,
      "text": "Kuala Krai",
      "label": "LOC",
      "score": 0.8320765495300293
    },
    {
      "start": 1694,
      "end": 1703,
      "text": "Wan Helmi",
      "label": "PERSON",
      "score": 0.8223370909690857
    }
  ],
  "https://www.sinarharian.com.my/article/708175/edisi/kelantan/perjanjian-adik-beradik-tingkatkan-jualan-peniaga": [
    {
      "start": 0,
      "end": 10,
      "text": "KOTA BHARU",
      "label": "LOC",
      "score": 0.8464128375053406
    },
    {
      "start": 13,
      "end": 54,
      "text": "Persatuan Batik dan Kraf Bazar Buluh Kubu",
      "label": "ORG",
      "score": 0.866104006767273
    },
    {
      "start": 59,
      "end": 113,
      "text": "Persatuan Peniaga Kecil Bumiputera Pasar Siti Khadijah",
      "label": "ORG",
      "score": 0.8273230195045471
    },
    {
      "start": 199,
      "end": 204,
      "text": "batik",
      "label": "PRODUCT",
      "score": 0.5489966869354248
    },
    {
      "start": 269,
      "end": 310,
      "text": "Persatuan Batik dan Kraf Bazar Buluh Kubu",
      "label": "ORG",
      "score": 0.6625053286552429
    },
    {
      "start": 312,
      "end": 342,
      "text": "Datin Nik Rosmawati Nik Yusoff",
      "label": "PERSON",
      "score": 0.6702383160591125
    },
    {
      "start": 362,
      "end": 365,
      "text": "100",
      "label": "QUANTITY",
      "score": 0.53298419713974
    },
    {
      "start": 415,
      "end": 418,
      "text": "350",
      "label": "QUANTITY",
      "score": 0.593904435634613
    },
    {
      "start": 424,
      "end": 461,
      "text": "Persatuan Peniaga Pasar Siti Khadijah",
      "label": "ORG",
      "score": 0.6706919074058533
    },
    {
      "start": 1106,
      "end": 1126,
      "text": "Ahmad Nazri Che Omar",
      "label": "PERSON",
      "score": 0.9349344968795776
    },
    {
      "start": 1127,
      "end": 1140,
      "text": "Nik Rosmawati",
      "label": "PERSON",
      "score": 0.5565076470375061
    },
    {
      "start": 1183,
      "end": 1192,
      "text": "dua tahun",
      "label": "TIME",
      "score": 0.6641180515289307
    },
    {
      "start": 1424,
      "end": 1434,
      "text": "Kota Bharu",
      "label": "LOC",
      "score": 0.8115260004997253
    },
    {
      "start": 1494,
      "end": 1504,
      "text": "RM5.5 juta",
      "label": "MONEY",
      "score": 0.8928322196006775
    },
    {
      "start": 2541,
      "end": 2551,
      "text": "Bank Islam",
      "label": "ORG",
      "score": 0.922402024269104
    }
  ],
  "https://www.sinarharian.com.my/article/708144/berita/semasa/semua-lenyap-sekelip-mata": [
    {
      "start": 0,
      "end": 11,
      "text": "PASIR PUTEH",
      "label": "LOC",
      "score": 0.811029851436615
    },
    {
      "start": 150,
      "end": 168,
      "text": "Kampung Alor Pasir",
      "label": "LOC",
      "score": 0.8456062078475952
    },
    {
      "start": 189,
      "end": 214,
      "text": "Muhammad Firdaus Mustapha",
      "label": "PERSON",
      "score": 0.9439769983291626
    },
    {
      "start": 369,
      "end": 375,
      "text": "isteri",
      "label": "PERSON",
      "score": 0.8069617748260498
    },
    {
      "start": 901,
      "end": 910,
      "text": "kebakaran",
      "label": "EVENT",
      "score": 0.5354905128479004
    },
    {
      "start": 1014,
      "end": 1020,
      "text": "isteri",
      "label": "PERSON",
      "score": 0.7943578362464905
    },
    {
      "start": 1233,
      "end": 1249,
      "text": "Muhammad Firdaus",
      "label": "PERSON",
      "score": 0.7917973399162292
    },
    {
      "start": 1406,
      "end": 1420,
      "text": "ribuan ringgit",
      "label": "MONEY",
      "score": 0.8273917436599731
    },
    {
      "start": 1865,
      "end": 1871,
      "text": "isteri",
      "label": "PERSON",
      "score": 0.8161500096321106
    },
    {
      "start": 1878,
      "end": 1887,
      "text": "anak-anak",
      "label": "PERSON",
      "score": 0.5452223420143127
    },
    {
      "start": 2071,
      "end": 2078,
      "text": "Maisara",
      "label": "PERSON",
      "score": 0.6128103137016296
    },
    {
      "start": 2088,
      "end": 2104,
      "text": "Muhammad Firdaus",
      "label": "PERSON",
      "score": 0.8329559564590454
    },
    {
      "start": 2263,
      "end": 2277,
      "text": "ribuan ringgit",
      "label": "MONEY",
      "score": 0.7767926454544067
    },
    {
      "start": 2371,
      "end": 2382,
      "text": "tujuh tahun",
      "label": "TIME",
      "score": 0.6565057039260864
    }
  ],
  "https://www.sinarharian.com.my/article/708011/edisi/utara/tangguh-spm-akibat-derita-kanser-ovari": [
    {
      "start": 0,
      "end": 8,
      "text": "CHANGLUN",
      "label": "LOC",
      "score": 0.7794191241264343
    },
    {
      "start": 182,
      "end": 205,
      "text": "Nur Auni Qistina Zahari",
      "label": "PERSON",
      "score": 0.82173752784729
    },
    {
      "start": 256,
      "end": 274,
      "text": "Bandar Baru Sintok",
      "label": "LOC",
      "score": 0.5595099329948425
    },
    {
      "start": 490,
      "end": 500,
      "text": "Alor Setar",
      "label": "LOC",
      "score": 0.7399976253509521
    },
    {
      "start": 655,
      "end": 663,
      "text": "Changlun",
      "label": "LOC",
      "score": 0.6680748462677002
    },
    {
      "start": 1030,
      "end": 1044,
      "text": "Zuraini Kamaln",
      "label": "PERSON",
      "score": 0.8852114677429199
    },
    {
      "start": 1068,
      "end": 1078,
      "text": "wang tunai",
      "label": "MONEY",
      "score": 0.9118260145187378
    },
    {
      "start": 1160,
      "end": 1168,
      "text": "Malaysia",
      "label": "LOC",
      "score": 0.5705773234367371
    },
    {
      "start": 1199,
      "end": 1207,
      "text": "Malaysia",
      "label": "LOC",
      "score": 0.5002785921096802
    },
    {
      "start": 1215,
      "end": 1230,
      "text": "Tahun Baru Cina",
      "label": "EVENT",
      "score": 0.6837129592895508
    },
    {
      "start": 1314,
      "end": 1330,
      "text": "Nur Auni Qistina",
      "label": "PERSON",
      "score": 0.6952313184738159
    },
    {
      "start": 1939,
      "end": 1957,
      "text": "Norhesreyzah Rejab",
      "label": "PERSON",
      "score": 0.8653417229652405
    },
    {
      "start": 2023,
      "end": 2036,
      "text": "Zahari Hashim",
      "label": "PERSON",
      "score": 0.8107820153236389
    },
    {
      "start": 2165,
      "end": 2181,
      "text": "Nur Auni Qistina",
      "label": "PERSON",
      "score": 0.7429863214492798
    },
    {
      "start": 2255,
      "end": 2273,
      "text": "Norhesreyzah Rejab",
      "label": "PERSON",
      "score": 0.8335022926330566
    }
  ],
  "https://www.sinarharian.com.my/article/707295/berita/semasa/nik-mohd-hasyudeen-dilantik-ahli-lembaga-pengarah-sc": [
    {
      "start": 0,
      "end": 9,
      "text": "SHAH ALAM",
      "label": "LOC",
      "score": 0.7350310683250427
    },
    {
      "start": 12,
      "end": 41,
      "text": "Suruhanjaya Sekuriti Malaysia",
      "label": "ORG",
      "score": 0.9382013082504272
    },
    {
      "start": 43,
      "end": 45,
      "text": "SC",
      "label": "ORG",
      "score": 0.6091071367263794
    },
    {
      "start": 56,
      "end": 87,
      "text": "Datuk Nik Mohd Hasyudeen Yusoff",
      "label": "PERSON",
      "score": 0.8560656905174255
    },
    {
      "start": 130,
      "end": 139,
      "text": "dua tahun",
      "label": "TIME",
      "score": 0.6191629767417908
    },
    {
      "start": 182,
      "end": 184,
      "text": "SC",
      "label": "ORG",
      "score": 0.6078863739967346
    },
    {
      "start": 186,
      "end": 210,
      "text": "Datuk Mohammad Faiz Azmi",
      "label": "PERSON",
      "score": 0.8347392678260803
    },
    {
      "start": 272,
      "end": 291,
      "text": "Lembaga Pengarah SC",
      "label": "ORG",
      "score": 0.6728832721710205
    },
    {
      "start": 348,
      "end": 350,
      "text": "SC",
      "label": "ORG",
      "score": 0.6218147277832031
    },
    {
      "start": 531,
      "end": 547,
      "text": "Lembaga Pengarah",
      "label": "ORG",
      "score": 0.5885297656059265
    },
    {
      "start": 548,
      "end": 550,
      "text": "SC",
      "label": "ORG",
      "score": 0.5678957104682922
    },
    {
      "start": 600,
      "end": 608,
      "text": "30 tahun",
      "label": "TIME",
      "score": 0.6252942681312561
    },
    {
      "start": 737,
      "end": 757,
      "text": "Program Felo Perdana",
      "label": "ORG",
      "score": 0.6607131361961365
    },
    {
      "start": 759,
      "end": 802,
      "text": "Petron Malaysia Refining & Marketing Berhad",
      "label": "ORG",
      "score": 0.9257904887199402
    },
    {
      "start": 807,
      "end": 833,
      "text": "Bank Islam Malaysia Berhad",
      "label": "ORG",
      "score": 0.9394257664680481
    },
    {
      "start": 890,
      "end": 908,
      "text": "Nik Mohd Hasyudeen",
      "label": "PERSON",
      "score": 0.550641655921936
    },
    {
      "start": 974,
      "end": 993,
      "text": "Lembaga Tabung Haji",
      "label": "ORG",
      "score": 0.6635642647743225
    },
    {
      "start": 1019,
      "end": 1021,
      "text": "SC",
      "label": "ORG",
      "score": 0.5251610279083252
    },
    {
      "start": 1108,
      "end": 1132,
      "text": "Lembaga Pemantauan Audit",
      "label": "ORG",
      "score": 0.695507287979126
    },
    {
      "start": 1161,
      "end": 1187,
      "text": "Institut Akauntan Malaysia",
      "label": "ORG",
      "score": 0.8090924024581909
    },
    {
      "start": 1194,
      "end": 1230,
      "text": "Lembaga Piawaian Perakaunan Malaysia",
      "label": "ORG",
      "score": 0.793657124042511
    },
    {
      "start": 1269,
      "end": 1325,
      "text": "Jawatankuasa Strategi Gabungan Akauntan Asia dan Pasifik",
      "label": "ORG",
      "score": 0.8492886424064636
    },
    {
      "start": 1391,
      "end": 1424,
      "text": "Fakulti Perniagaan dan Perakaunan",
      "label": "ORG",
      "score": 0.5877108573913574
    },
    {
      "start": 1496,
      "end": 1523,
      "text": "Universiti Teknologi Curtin",
      "label": "ORG",
      "score": 0.7402888536453247
    },
    {
      "start": 1525,
      "end": 1530,
      "text": "Perth",
      "label": "LOC",
      "score": 0.6684957146644592
    },
    {
      "start": 1532,
      "end": 1547,
      "text": "Australia Barat",
      "label": "LOC",
      "score": 0.5639988780021667
    },
    {
      "start": 1568,
      "end": 1583,
      "text": "Kamaruddin Mape",
      "label": "PERSON",
      "score": 0.9144537448883057
    },
    {
      "start": 1607,
      "end": 1654,
      "text": "Panel Perundingan dan Pencegahan Rasuah SPRMSah",
      "label": "ORG",
      "score": 0.6023726463317871
    },
    {
      "start": 1696,
      "end": 1701,
      "text": "Zahid",
      "label": "PERSON",
      "score": 0.7662350535392761
    },
    {
      "start": 1758,
      "end": 1776,
      "text": "Suruhanjaya Tenaga",
      "label": "ORG",
      "score": 0.7392192482948303
    },
    {
      "start": 1822,
      "end": 1834,
      "text": "Sinar Harian",
      "label": "ORG",
      "score": 0.8018630743026733
    }
  ],
  "https://www.sinarharian.com.my/article/707125/bisnes/bank-islam-biaya-projek-solar-rm1052-juta-dengan-solar-voltech": [
    {
      "start": 14,
      "end": 24,
      "text": "Bank Islam",
      "label": "ORG",
      "score": 0.9409117102622986
    },
    {
      "start": 77,
      "end": 89,
      "text": "RM105.2 juta",
      "label": "MONEY",
      "score": 0.9644685387611389
    },
    {
      "start": 97,
      "end": 110,
      "text": "Solar Voltech",
      "label": "ORG",
      "score": 0.8724768161773682
    },
    {
      "start": 193,
      "end": 206,
      "text": "Solar Voltech",
      "label": "ORG",
      "score": 0.7402677536010742
    },
    {
      "start": 249,
      "end": 284,
      "text": "Perbadanan Pembangunan Pulau Pinang",
      "label": "ORG",
      "score": 0.6469100713729858
    },
    {
      "start": 343,
      "end": 353,
      "text": "Bank Islam",
      "label": "ORG",
      "score": 0.787175178527832
    },
    {
      "start": 371,
      "end": 397,
      "text": "Datuk Mohd Muazzam Mohamed",
      "label": "PERSON",
      "score": 0.8422195911407471
    },
    {
      "start": 531,
      "end": 541,
      "text": "Bank Islam",
      "label": "ORG",
      "score": 0.8538178205490112
    },
    {
      "start": 865,
      "end": 875,
      "text": "Bank Islam",
      "label": "ORG",
      "score": 0.8665122389793396
    },
    {
      "start": 883,
      "end": 896,
      "text": "Solar Voltech",
      "label": "ORG",
      "score": 0.7770428657531738
    },
    {
      "start": 1003,
      "end": 1015,
      "text": "RM105.2 juta",
      "label": "MONEY",
      "score": 0.9765458703041077
    },
    {
      "start": 1175,
      "end": 1185,
      "text": "Bank Islam",
      "label": "ORG",
      "score": 0.8735070824623108
    },
    {
      "start": 1206,
      "end": 1227,
      "text": "Solar Voltech Sdn Bhd",
      "label": "ORG",
      "score": 0.7472904920578003
    },
    {
      "start": 1258,
      "end": 1263,
      "text": "Petra",
      "label": "ORG",
      "score": 0.6840451955795288
    },
    {
      "start": 1296,
      "end": 1308,
      "text": "RM186.1 juta",
      "label": "MONEY",
      "score": 0.9361794590950012
    },
    {
      "start": 1316,
      "end": 1331,
      "text": "JohorBank Islam",
      "label": "ORG",
      "score": 0.5937461853027344
    },
    {
      "start": 1403,
      "end": 1423,
      "text": "RM1.4 jutaPerjanjian",
      "label": "MONEY",
      "score": 0.8400017619132996
    },
    {
      "start": 1508,
      "end": 1518,
      "text": "Bank Islam",
      "label": "ORG",
      "score": 0.8068338632583618
    },
    {
      "start": 1520,
      "end": 1550,
      "text": "Sharifah Sarah Syed Mohd Tahir",
      "label": "PERSON",
      "score": 0.8962433338165283
    },
    {
      "start": 1580,
      "end": 1601,
      "text": "Solar Voltech Sdn Bhd",
      "label": "ORG",
      "score": 0.7640069127082825
    },
    {
      "start": 1603,
      "end": 1618,
      "text": "Izwanaim Ismail",
      "label": "PERSON",
      "score": 0.8958834409713745
    },
    {
      "start": 1635,
      "end": 1645,
      "text": "Bank Islam",
      "label": "ORG",
      "score": 0.7984440326690674
    },
    {
      "start": 1799,
      "end": 1809,
      "text": "Bank Islam",
      "label": "ORG",
      "score": 0.7967638373374939
    },
    {
      "start": 2002,
      "end": 2014,
      "text": "RM105.2 juta",
      "label": "MONEY",
      "score": 0.9712340831756592
    },
    {
      "start": 2096,
      "end": 2106,
      "text": "Bank Islam",
      "label": "ORG",
      "score": 0.8187740445137024
    },
    {
      "start": 2137,
      "end": 2150,
      "text": "RM4.96 bilion",
      "label": "MONEY",
      "score": 0.9378638863563538
    },
    {
      "start": 2295,
      "end": 2307,
      "text": "58.1 peratus",
      "label": "PERCENT",
      "score": 0.7803272604942322
    },
    {
      "start": 2468,
      "end": 2478,
      "text": "Bank Islam",
      "label": "ORG",
      "score": 0.8295513391494751
    }
  ],
  "https://prpm.dbp.gov.my/Cari1?keyword=bank+islam": [
    {
      "start": 11,
      "end": 15,
      "text": "bank",
      "label": "ORG",
      "score": 0.9594679474830627
    },
    {
      "start": 54,
      "end": 61,
      "text": "dananya",
      "label": "MONEY",
      "score": 0.6583107709884644
    },
    {
      "start": 74,
      "end": 87,
      "text": "syariat Islam",
      "label": "LAW",
      "score": 0.6505483984947205
    }
  ]
}